post_velocity/__init__.py
post_velocity/post_velocity.py
post_velocity-0.1.2.dist-info/LICENSE
post_velocity-0.1.2.dist-info/METADATA
post_velocity-0.1.2.dist-info/WHEEL
post_velocity-0.1.2.dist-info/top_level.txt
post_velocity-0.1.2.dist-info/RECORD
