Metadata-Version: 2.1
Name: post-velocity
Version: 0.1.2
Summary: Package to compute Bayesian posterior distribution for transversal velocity using parallaxes and proper motions.
Author-email: "Andrei P. Igoshev" <ignotur@gmail.com>
Project-URL: Homepage, https://github.com/ignotur/post-velocity
Project-URL: Bug Tracker, https://github.com/ignotur/post-velocity/issues
Classifier: Programming Language :: Python :: 3
Classifier: License :: OSI Approved :: GNU General Public License v3 (GPLv3)
Classifier: Operating System :: OS Independent
Requires-Python: >=3.7
License-File: LICENSE
